[
  {
    "id": 1,
    "title": "Comment ouvrir une porte",
    "description": "Technique révolutionnaire pour ne pas casser la poignée",
    "duration": "15 min",
    "difficulty": "Expert",
    "rating": 4.9,
    "students": 2847,
    "image": "https://images.pexels.com/photos/277574/pexels-photo-277574.jpeg?auto=compress&cs=tinysrgb&w=800",
    "category": "Manipulation d'objets"
  },
  {
    "id": 2,
    "title": "L'art de rater son CV",
    "description": "Maximisez vos chances de refus avec ces techniques éprouvées",
    "duration": "22 min",
    "difficulty": "Débutant",
    "rating": 4.8,
    "students": 5621,
    "image": "https://images.pexels.com/photos/590016/pexels-photo-590016.jpg?auto=compress&cs=tinysrgb&w=800",
    "category": "Carrière professionnelle"
  },
  {
    "id": 3,
    "title": "S'asseoir sur une chaise",
    "description": "Guide complet étape par étape pour débutants",
    "duration": "8 min",
    "difficulty": "Novice",
    "rating": 5.0,
    "students": 12453,
    "image": "https://images.pexels.com/photos/586000/pexels-photo-586000.jpg?auto=compress&cs=tinysrgb&w=800",
    "category": "Bases de la vie"
  },
  {
    "id": 4,
    "title": "Faire des noeuds impossibles",
    "description": "Transformez n'importe quel câble en puzzle insoluble",
    "duration": "18 min",
    "difficulty": "Maître",
    "rating": 4.7,
    "students": 892,
    "image": "https://images.pexels.com/photos/1770809/pexels-photo-1770809.jpg?auto=compress&cs=tinysrgb&w=800",
    "category": "Arts appliqués"
  },
  {
    "id": 5,
    "title": "Perdre ses clés efficacement",
    "description": "Méthodes scientifiques pour égarer vos affaires",
    "duration": "12 min",
    "difficulty": "Intermédiaire",
    "rating": 4.6,
    "students": 3245,
    "image": "https://images.pexels.com/photos/1698528/pexels-photo-1698528.jpg?auto=compress&cs=tinysrgb&w=800",
    "category": "Organisation personnelle"
  },
  {
    "id": 6,
    "title": "Faire semblant de comprendre",
    "description": "L'art de hocher la tête de manière convaincante",
    "duration": "25 min",
    "difficulty": "Expert",
    "rating": 4.9,
    "students": 7892,
    "image": "https://images.pexels.com/photos/3184298/pexels-photo-3184298.jpg?auto=compress&cs=tinysrgb&w=800",
    "category": "Communication sociale"
  },
  {
    "id": 7,
    "title": "Marcher sans but dans une pièce",
    "description": "Comment avoir l'air occupé quand vous ne faites rien",
    "duration": "10 min",
    "difficulty": "Débutant",
    "rating": 4.5,
    "students": 2011,
    "image": "https://images.pexels.com/photos/317157/pexels-photo-317157.jpeg?auto=compress&cs=tinysrgb&w=800",
    "category": "Productivité illusoire"
  },
  {
    "id": 8,
    "title": "Ignorer les notifications comme un pro",
    "description": "Développez une zen attitude face à 87 messages non lus",
    "duration": "16 min",
    "difficulty": "Intermédiaire",
    "rating": 4.8,
    "students": 4389,
    "image": "https://images.pexels.com/photos/267569/pexels-photo-267569.jpeg?auto=compress&cs=tinysrgb&w=800",
    "category": "Santé mentale numérique"
  },
  {
    "id": 9,
    "title": "Plier un t-shirt... mal",
    "description": "La méthode ultime pour le sortir toujours froissé",
    "duration": "9 min",
    "difficulty": "Novice",
    "rating": 4.2,
    "students": 1432,
    "image": "https://images.pexels.com/photos/19090/pexels-photo.jpg?auto=compress&cs=tinysrgb&w=800",
    "category": "Entretien ménager désastreux"
  },
  {
    "id": 10,
    "title": "Appuyer frénétiquement sur un bouton",
    "description": "Pour ceux qui pensent que ça va plus vite",
    "duration": "6 min",
    "difficulty": "Débutant",
    "rating": 4.4,
    "students": 982,
    "image": "https://images.pexels.com/photos/1043698/pexels-photo-1043698.jpeg?auto=compress&cs=tinysrgb&w=800",
    "category": "Technologie archaïque"
  },
  {
    "id": 11,
    "title": "Répondre \"Je sais pas\" avec assurance",
    "description": "Soyez convaincant même sans la moindre idée",
    "duration": "20 min",
    "difficulty": "Expert",
    "rating": 4.9,
    "students": 3478,
    "image": "https://images.pexels.com/photos/3771833/pexels-photo-3771833.jpeg?auto=compress&cs=tinysrgb&w=800",
    "category": "Communication improvisée"
  },
  {
    "id": 12,
    "title": "Mettre des chaussettes mouillées",
    "description": "Expérience sensorielle unique, déconseillée par tous",
    "duration": "5 min",
    "difficulty": "Héroïque",
    "rating": 4.1,
    "students": 652,
    "image": "https://images.pexels.com/photos/19090/pexels-photo-19090.jpeg?auto=compress&cs=tinysrgb&w=800",
    "category": "Expériences extrêmes"
  }
]
